style/__init__.py
style/ansi.py
style/styled_string.py
style/styled_string_builder.py
style-1.1.6.dist-info/LICENSE
style-1.1.6.dist-info/METADATA
style-1.1.6.dist-info/WHEEL
style-1.1.6.dist-info/top_level.txt
style-1.1.6.dist-info/zip-safe
style-1.1.6.dist-info/RECORD
