Metadata-Version: 1.1
Name: style
Version: 1.1.6
Summary: 🌈 Terminal string styling
Home-page: https://github.com/lmittmann/style
Author: lmittmann
Author-email: UNKNOWN
License: MIT
Keywords: style,color,ansi,terminal styling,chalk
Platform: UNKNOWN
Classifier: Development Status :: 5 - Production/Stable
Classifier: Intended Audience :: Developers
Classifier: License :: OSI Approved :: MIT License
Classifier: Natural Language :: English
Classifier: Programming Language :: Python :: 2.7
Classifier: Programming Language :: Python :: 3
Classifier: Programming Language :: Python :: 3.5
Classifier: Programming Language :: Python :: 3.6
